ovos_ww_plugin_vosk/__init__.py
ovos_ww_plugin_vosk/version.py
ovos_ww_plugin_vosk-0.1.10.dist-info/licenses/LICENSE
ovos_ww_plugin_vosk-0.1.10.dist-info/METADATA
ovos_ww_plugin_vosk-0.1.10.dist-info/WHEEL
ovos_ww_plugin_vosk-0.1.10.dist-info/entry_points.txt
ovos_ww_plugin_vosk-0.1.10.dist-info/top_level.txt
ovos_ww_plugin_vosk-0.1.10.dist-info/zip-safe
ovos_ww_plugin_vosk-0.1.10.dist-info/RECORD
