Metadata-Version: 2.4
Name: ovos_ww_plugin_vosk
Version: 0.1.10
Summary: Kaldi wake word plugin for mycroft
Home-page: https://github.com/OpenVoiceOS/ovos-ww-plugin-vosk
Author: JarbasAi
Author-email: jarbasai@mailfence.com
License: Apache-2.0
Keywords: mycroft ovos plugin wake word
Classifier: Development Status :: 3 - Alpha
Classifier: Intended Audience :: Developers
Classifier: License :: OSI Approved :: Apache Software License
License-File: LICENSE
Requires-Dist: numpy
Requires-Dist: vosk
Requires-Dist: ovos-plugin-manager<3.0.0,>=2.1.1
Requires-Dist: ovos-bus-client>=0.0.6
Dynamic: author
Dynamic: author-email
Dynamic: classifier
Dynamic: home-page
Dynamic: keywords
Dynamic: license
Dynamic: license-file
Dynamic: requires-dist
Dynamic: summary
